ics_2000/__init__.py
ics_2000/command.py
ics_2000/config.py
ics_2000/encryption.py
ics_2000/entities/__init__.py
ics_2000/entities/color_temperature_device.py
ics_2000/entities/device.py
ics_2000/entities/dim_device.py
ics_2000/entities/entity.py
ics_2000/entities/switch_device.py
ics_2000/exceptions.py
ics_2000/hub.py
ics_2000/model/__init__.py
ics_2000/model/device_config.py
ics_2000/model/device_data.py
ics_2000/model/entity_type.py
ics_2000/model/smart_meter_data.py
ics_2000/model/smart_meter_data_current.py
ics_2000_python-0.1.3.dist-info/LICENSE
ics_2000_python-0.1.3.dist-info/METADATA
ics_2000_python-0.1.3.dist-info/WHEEL
ics_2000_python-0.1.3.dist-info/RECORD
