Metadata-Version: 2.3
Name: ics_2000_python
Version: 0.1.3
Summary: 
Keywords: ics_2000,ics-2000,klikaanklikuit
Author: iiTzArcur
Author-email: zefanjaj@gmail.com
Requires-Python: >=3.12,<4.0
Classifier: Programming Language :: Python :: 3
Classifier: Programming Language :: Python :: 3.12
Classifier: Programming Language :: Python :: 3.13
Requires-Dist: pycryptodome (>=3.21.0,<4.0.0)
Requires-Dist: requests (>=2.32.3,<3.0.0)
Project-URL: Repository, https://github.com/zefanjajobse/ics_2000_python
